grpcAPI/__init__.py
grpcAPI/_version.py
grpcAPI/add_to_server.py
grpcAPI/app.py
grpcAPI/build_proto.py
grpcAPI/cli.py
grpcAPI/ctxinject_proto.py
grpcAPI/datatypes.py
grpcAPI/label_method.py
grpcAPI/load_credential.py
grpcAPI/logger.py
grpcAPI/make_method.py
grpcAPI/server.py
grpcAPI/singleton.py
grpcAPI/typehint_proto.py
grpcAPI/utils.py
grpcAPI/commands/__init__.py
grpcAPI/commands/build.py
grpcAPI/commands/command.py
grpcAPI/commands/init.py
grpcAPI/commands/lint.py
grpcAPI/commands/list.py
grpcAPI/commands/protoc.py
grpcAPI/commands/run.py
grpcAPI/commands/settings/__init__.py
grpcAPI/commands/settings/config.json
grpcAPI/commands/settings/utils.py
grpcAPI/makeproto/__init__.py
grpcAPI/makeproto/build_service.py
grpcAPI/makeproto/compiler.py
grpcAPI/makeproto/compiler_passes.py
grpcAPI/makeproto/files_sentinel.py
grpcAPI/makeproto/format_comment.py
grpcAPI/makeproto/interface.py
grpcAPI/makeproto/make_service_template.py
grpcAPI/makeproto/report.py
grpcAPI/makeproto/template.py
grpcAPI/makeproto/write_proto.py
grpcAPI/makeproto/setters/__init__.py
grpcAPI/makeproto/setters/comment.py
grpcAPI/makeproto/setters/imports.py
grpcAPI/makeproto/setters/name.py
grpcAPI/makeproto/setters/service.py
grpcAPI/makeproto/setters/type.py
grpcAPI/makeproto/templates/protofile.j2
grpcAPI/makeproto/templates/service.j2
grpcAPI/makeproto/validators/comment.py
grpcAPI/makeproto/validators/custommethod.py
grpcAPI/makeproto/validators/imports.py
grpcAPI/makeproto/validators/name.py
grpcAPI/makeproto/validators/type.py
grpcAPI/protobuf/__init__.py
grpcAPI/protobuf/deriveds.py
grpcAPI/protoc/__init__.py
grpcAPI/protoc/__main__.py
grpcAPI/protoc/compile.py
grpcAPI/server_plugins/__init__.py
grpcAPI/server_plugins/loader.py
grpcAPI/server_plugins/plugins/__init__.py
grpcAPI/server_plugins/plugins/health_check.py
grpcAPI/server_plugins/plugins/reflection.py
grpcAPI/server_plugins/plugins/server_logger.py
grpcAPI/service_proc/__init__.py
grpcAPI/service_proc/add_gateway.py
grpcapi-0.1.2.dist-info/licenses/LICENSE
grpcapi-0.1.2.dist-info/METADATA
grpcapi-0.1.2.dist-info/WHEEL
grpcapi-0.1.2.dist-info/entry_points.txt
grpcapi-0.1.2.dist-info/top_level.txt
grpcapi-0.1.2.dist-info/RECORD
